plajira/__init__.py
plajira/__main__.py
plajira/cli.py
plajira/config.py
plajira/diff.py
plajira/git_reader.py
plajira/jira_client.py
plajira/plan_parser.py
plajira/similarity.py
plajira/sync.py
plajira/ui.py
plajira-0.4.0.dist-info/licenses/LICENSE
plajira-0.4.0.dist-info/METADATA
plajira-0.4.0.dist-info/WHEEL
plajira-0.4.0.dist-info/entry_points.txt
plajira-0.4.0.dist-info/top_level.txt
plajira-0.4.0.dist-info/RECORD
