Metadata-Version: 2.4
Name: plajira
Version: 0.4.0
Summary: Sync your .plan file with Jira Cloud
Author: plajira contributors
License: MIT
Project-URL: Homepage, https://github.com/plajira
Project-URL: Repository, https://github.com/plajira/plajira
Project-URL: Issues, https://github.com/plajira/plajira/issues
Keywords: jira,plan,sync,productivity,cli
Classifier: Development Status :: 4 - Beta
Classifier: Environment :: Console
Classifier: Intended Audience :: Developers
Classifier: License :: OSI Approved :: MIT License
Classifier: Operating System :: OS Independent
Classifier: Programming Language :: Python :: 3
Classifier: Programming Language :: Python :: 3.8
Classifier: Programming Language :: Python :: 3.9
Classifier: Programming Language :: Python :: 3.10
Classifier: Programming Language :: Python :: 3.11
Classifier: Programming Language :: Python :: 3.12
Classifier: Programming Language :: Python :: 3.13
Classifier: Topic :: Software Development :: Bug Tracking
Classifier: Topic :: Utilities
Requires-Python: >=3.8
License-File: LICENSE
Dynamic: license-file
